odoo/addons/account_statement_import_online_gocardless/README.rst
odoo/addons/account_statement_import_online_gocardless/__init__.py
odoo/addons/account_statement_import_online_gocardless/__manifest__.py
odoo/addons/account_statement_import_online_gocardless/controllers/__init__.py
odoo/addons/account_statement_import_online_gocardless/controllers/main.py
odoo/addons/account_statement_import_online_gocardless/i18n/account_statement_import_online_gocardless.pot
odoo/addons/account_statement_import_online_gocardless/i18n/ca.po
odoo/addons/account_statement_import_online_gocardless/i18n/es.po
odoo/addons/account_statement_import_online_gocardless/i18n/it.po
odoo/addons/account_statement_import_online_gocardless/models/__init__.py
odoo/addons/account_statement_import_online_gocardless/models/online_bank_statement_provider.py
odoo/addons/account_statement_import_online_gocardless/readme/CONFIGURE.md
odoo/addons/account_statement_import_online_gocardless/readme/CONTRIBUTORS.md
odoo/addons/account_statement_import_online_gocardless/readme/DESCRIPTION.md
odoo/addons/account_statement_import_online_gocardless/readme/USAGE.md
odoo/addons/account_statement_import_online_gocardless/security/ir.model.access.csv
odoo/addons/account_statement_import_online_gocardless/static/description/icon.png
odoo/addons/account_statement_import_online_gocardless/static/description/index.html
odoo/addons/account_statement_import_online_gocardless/static/img/gocardless_bank_selection.png
odoo/addons/account_statement_import_online_gocardless/static/img/gocardless_configuration.png
odoo/addons/account_statement_import_online_gocardless/static/src/js/select_bank_widget.esm.js
odoo/addons/account_statement_import_online_gocardless/static/src/lib/gocardless-ui/selector.css
odoo/addons/account_statement_import_online_gocardless/static/src/lib/gocardless-ui/fonts/HKGrotesk-Bold.ttf
odoo/addons/account_statement_import_online_gocardless/static/src/lib/gocardless-ui/fonts/HKGrotesk-SemiBold.ttf
odoo_addon_account_statement_import_online_gocardless-18.0.1.0.0.3.dist-info/METADATA
odoo_addon_account_statement_import_online_gocardless-18.0.1.0.0.3.dist-info/WHEEL
odoo_addon_account_statement_import_online_gocardless-18.0.1.0.0.3.dist-info/top_level.txt
odoo_addon_account_statement_import_online_gocardless-18.0.1.0.0.3.dist-info/RECORD
