Metadata-Version: 2.1
Name: odoo-addon-account_statement_import_online_gocardless
Version: 18.0.1.0.0.3
Requires-Python: >=3.10
Requires-Dist: odoo-addon-account_statement_import_online==18.0.*
Requires-Dist: odoo==18.0.*
Summary: Online Bank Statements: GoCardless
Home-page: https://github.com/OCA/bank-statement-import
License: AGPL-3
Author: ForgeFlow, Tecnativa, Odoo Community Association (OCA)
Author-email: support@odoo-community.org
Classifier: Programming Language :: Python
Classifier: Framework :: Odoo
Classifier: Framework :: Odoo :: 18.0
Classifier: License :: OSI Approved :: GNU Affero General Public License v3
